voiceform_fill/__init__.py
voiceform_fill/main.py
voiceform_fill/prompts.py
voiceform_fill-2025.12.22111543.dist-info/METADATA
voiceform_fill-2025.12.22111543.dist-info/WHEEL
voiceform_fill-2025.12.22111543.dist-info/top_level.txt
voiceform_fill-2025.12.22111543.dist-info/RECORD
