Metadata-Version: 2.4
Name: voiceform-fill
Version: 2025.12.22111543
Summary: voiceform‑fill turns spoken answers into structured form text using advanced models, enabling hands‑free, accurate data entry.
Author-email: voiceform-fill <hi@eugene.plus>
License: MIT
Project-URL: Homepage, https://github.com/chigwell/voiceform-fill
Requires-Python: >=3.9
Requires-Dist: langchain-llm7>=0.0.0
Requires-Dist: llmatch-messages>=0.0.0
Requires-Dist: langchain-core>=0.3.0
